{
  "task_id": "DISCOVERY_GAPPERS",
  "symbols": [
    {
      "symbol": "FONR",
      "rank": 1,
      "dominance_score": 39.3,
      "gap_pct": 27.08,
      "rel_vol_daily": null,
      "rel_vol_5m": null,
      "volume_today": 1135586,
      "pct_gain": 27.08,
      "price": 18.63,
      "hod_price": 18.86,
      "pct_from_hod": -1.22,
      "at_hod": false,
      "near_hod": true,
      "is_active": true,
      "exclusion_reason": "NONE",
      "first_seen": "2025-12-30T23:24:18.719224+00:00",
      "last_evaluated": "2025-12-30T23:24:18.719224+00:00",
      "session_date": "2025-12-30",
      "has_valid_rel_vol": false,
      "has_valid_price": true,
      "hod_status": "NEAR_HOD",
      "priority": "LOW"
    },
    {
      "symbol": "ZBAI",
      "rank": 2,
      "dominance_score": 32.91,
      "gap_pct": 29.93,
      "rel_vol_daily": null,
      "rel_vol_5m": null,
      "volume_today": 77172,
      "pct_gain": 29.93,
      "price": 5.22,
      "hod_price": 6.28,
      "pct_from_hod": -16.88,
      "at_hod": false,
      "near_hod": false,
      "is_active": true,
      "exclusion_reason": "NONE",
      "first_seen": "2025-12-30T23:24:18.719224+00:00",
      "last_evaluated": "2025-12-30T23:24:18.719224+00:00",
      "session_date": "2025-12-30",
      "has_valid_rel_vol": false,
      "has_valid_price": true,
      "hod_status": "PULLBACK",
      "priority": "LOW"
    },
    {
      "symbol": "ANL",
      "rank": 3,
      "dominance_score": 21.04,
      "gap_pct": 20.56,
      "rel_vol_daily": null,
      "rel_vol_5m": null,
      "volume_today": 604265,
      "pct_gain": 20.56,
      "price": 1.43,
      "hod_price": 1.76,
      "pct_from_hod": -18.75,
      "at_hod": false,
      "near_hod": false,
      "is_active": true,
      "exclusion_reason": "NONE",
      "first_seen": "2025-12-30T23:24:18.719224+00:00",
      "last_evaluated": "2025-12-30T23:24:18.719224+00:00",
      "session_date": "2025-12-30",
      "has_valid_rel_vol": false,
      "has_valid_price": true,
      "hod_status": "PULLBACK",
      "priority": "LOW"
    },
    {
      "symbol": "NKLR",
      "rank": 4,
      "dominance_score": 18.76,
      "gap_pct": 14.81,
      "rel_vol_daily": null,
      "rel_vol_5m": null,
      "volume_today": 1664901,
      "pct_gain": 14.81,
      "price": 4.73,
      "hod_price": 4.84,
      "pct_from_hod": -2.27,
      "at_hod": false,
      "near_hod": false,
      "is_active": true,
      "exclusion_reason": "NONE",
      "first_seen": "2025-12-30T23:24:18.719224+00:00",
      "last_evaluated": "2025-12-30T23:24:18.719224+00:00",
      "session_date": "2025-12-30",
      "has_valid_rel_vol": false,
      "has_valid_price": true,
      "hod_status": "PULLBACK",
      "priority": "LOW"
    },
    {
      "symbol": "WOK",
      "rank": 5,
      "dominance_score": 18.41,
      "gap_pct": 18.48,
      "rel_vol_daily": null,
      "rel_vol_5m": null,
      "volume_today": 993595,
      "pct_gain": 18.48,
      "price": 2.78,
      "hod_price": 3.3,
      "pct_from_hod": -15.76,
      "at_hod": false,
      "near_hod": false,
      "is_active": true,
      "exclusion_reason": "NONE",
      "first_seen": "2025-12-30T23:24:18.719224+00:00",
      "last_evaluated": "2025-12-30T23:24:18.719224+00:00",
      "session_date": "2025-12-30",
      "has_valid_rel_vol": false,
      "has_valid_price": true,
      "hod_status": "PULLBACK",
      "priority": "LOW"
    },
    {
      "symbol": "TTRX",
      "rank": 6,
      "dominance_score": 17.99,
      "gap_pct": 18.15,
      "rel_vol_daily": null,
      "rel_vol_5m": null,
      "volume_today": 109918,
      "pct_gain": 18.15,
      "price": 3.71,
      "hod_price": 3.93,
      "pct_from_hod": -5.6,
      "at_hod": false,
      "near_hod": false,
      "is_active": true,
      "exclusion_reason": "NONE",
      "first_seen": "2025-12-30T23:24:18.719224+00:00",
      "last_evaluated": "2025-12-30T23:24:18.719224+00:00",
      "session_date": "2025-12-30",
      "has_valid_rel_vol": false,
      "has_valid_price": true,
      "hod_status": "PULLBACK",
      "priority": "LOW"
    },
    {
      "symbol": "TROO",
      "rank": 7,
      "dominance_score": 17.75,
      "gap_pct": 17.96,
      "rel_vol_daily": null,
      "rel_vol_5m": null,
      "volume_today": 365515,
      "pct_gain": 17.96,
      "price": 2.89,
      "hod_price": 3.18,
      "pct_from_hod": -9.12,
      "at_hod": false,
      "near_hod": false,
      "is_active": true,
      "exclusion_reason": "NONE",
      "first_seen": "2025-12-30T23:24:18.719224+00:00",
      "last_evaluated": "2025-12-30T23:24:18.719224+00:00",
      "session_date": "2025-12-30",
      "has_valid_rel_vol": false,
      "has_valid_price": true,
      "hod_status": "PULLBACK",
      "priority": "LOW"
    },
    {
      "symbol": "SOPA",
      "rank": 8,
      "dominance_score": 16.18,
      "gap_pct": 16.72,
      "rel_vol_daily": null,
      "rel_vol_5m": null,
      "volume_today": 39270587,
      "pct_gain": 16.72,
      "price": 3.41,
      "hod_price": 3.8,
      "pct_from_hod": -10.26,
      "at_hod": false,
      "near_hod": false,
      "is_active": true,
      "exclusion_reason": "NONE",
      "first_seen": "2025-12-30T23:24:18.719224+00:00",
      "last_evaluated": "2025-12-30T23:24:18.719224+00:00",
      "session_date": "2025-12-30",
      "has_valid_rel_vol": false,
      "has_valid_price": true,
      "hod_status": "PULLBACK",
      "priority": "LOW"
    },
    {
      "symbol": "NOMA",
      "rank": 9,
      "dominance_score": 15.3,
      "gap_pct": 16.03,
      "rel_vol_daily": null,
      "rel_vol_5m": null,
      "volume_today": 243470,
      "pct_gain": 16.03,
      "price": 4.4,
      "hod_price": 5.31,
      "pct_from_hod": -17.14,
      "at_hod": false,
      "near_hod": false,
      "is_active": true,
      "exclusion_reason": "NONE",
      "first_seen": "2025-12-30T23:24:18.719224+00:00",
      "last_evaluated": "2025-12-30T23:24:18.719224+00:00",
      "session_date": "2025-12-30",
      "has_valid_rel_vol": false,
      "has_valid_price": true,
      "hod_status": "PULLBACK",
      "priority": "LOW"
    },
    {
      "symbol": "BNAI",
      "rank": 10,
      "dominance_score": 13.04,
      "gap_pct": 14.24,
      "rel_vol_daily": null,
      "rel_vol_5m": null,
      "volume_today": 5289675,
      "pct_gain": 14.24,
      "price": 2.14,
      "hod_price": 2.7299,
      "pct_from_hod": -21.61,
      "at_hod": false,
      "near_hod": false,
      "is_active": true,
      "exclusion_reason": "NONE",
      "first_seen": "2025-12-30T23:24:18.719224+00:00",
      "last_evaluated": "2025-12-30T23:24:18.719224+00:00",
      "session_date": "2025-12-30",
      "has_valid_rel_vol": false,
      "has_valid_price": true,
      "hod_status": "PULLBACK",
      "priority": "LOW"
    }
  ],
  "symbol_count": 10,
  "recompute_model": "FULL_RECOMPUTE",
  "filter_criteria": {
    "max_active_symbols": 10,
    "min_rel_vol_floor": 0.3,
    "min_price": 1.0,
    "max_price": 20.0,
    "min_gap_pct": 2.0,
    "enforce_session_boundary": true
  },
  "data_quality_summary": {
    "total_evaluated": 28,
    "float_missing_count": 28,
    "avg_volume_missing_count": 28,
    "hod_inconsistent_count": 14,
    "rel_vol_absurd_count": 0
  },
  "rank_snapshot": {
    "cycle_number": 1,
    "session_date": "2025-12-30",
    "timestamp": "2025-12-30T23:24:18.719224+00:00",
    "config": {
      "max_active_symbols": 10,
      "min_rel_vol_floor": 0.3,
      "min_price": 1.0,
      "max_price": 20.0,
      "min_gap_pct": 2.0,
      "enforce_session_boundary": true
    },
    "total_candidates": 28,
    "passed_filters": 28,
    "excluded_count": 0,
    "active_count": 10,
    "below_cutoff_count": 18,
    "active_watchlist": [
      {
        "symbol": "FONR",
        "rank": 1,
        "dominance_score": 39.3,
        "gap_pct": 27.08,
        "rel_vol_daily": null,
        "rel_vol_5m": null,
        "volume_today": 1135586,
        "pct_gain": 27.08,
        "price": 18.63,
        "hod_price": 18.86,
        "pct_from_hod": -1.22,
        "at_hod": false,
        "near_hod": true,
        "is_active": true,
        "exclusion_reason": "NONE",
        "first_seen": "2025-12-30T23:24:18.719224+00:00",
        "last_evaluated": "2025-12-30T23:24:18.719224+00:00",
        "session_date": "2025-12-30",
        "has_valid_rel_vol": false,
        "has_valid_price": true
      },
      {
        "symbol": "ZBAI",
        "rank": 2,
        "dominance_score": 32.91,
        "gap_pct": 29.93,
        "rel_vol_daily": null,
        "rel_vol_5m": null,
        "volume_today": 77172,
        "pct_gain": 29.93,
        "price": 5.22,
        "hod_price": 6.28,
        "pct_from_hod": -16.88,
        "at_hod": false,
        "near_hod": false,
        "is_active": true,
        "exclusion_reason": "NONE",
        "first_seen": "2025-12-30T23:24:18.719224+00:00",
        "last_evaluated": "2025-12-30T23:24:18.719224+00:00",
        "session_date": "2025-12-30",
        "has_valid_rel_vol": false,
        "has_valid_price": true
      },
      {
        "symbol": "ANL",
        "rank": 3,
        "dominance_score": 21.04,
        "gap_pct": 20.56,
        "rel_vol_daily": null,
        "rel_vol_5m": null,
        "volume_today": 604265,
        "pct_gain": 20.56,
        "price": 1.43,
        "hod_price": 1.76,
        "pct_from_hod": -18.75,
        "at_hod": false,
        "near_hod": false,
        "is_active": true,
        "exclusion_reason": "NONE",
        "first_seen": "2025-12-30T23:24:18.719224+00:00",
        "last_evaluated": "2025-12-30T23:24:18.719224+00:00",
        "session_date": "2025-12-30",
        "has_valid_rel_vol": false,
        "has_valid_price": true
      },
      {
        "symbol": "NKLR",
        "rank": 4,
        "dominance_score": 18.76,
        "gap_pct": 14.81,
        "rel_vol_daily": null,
        "rel_vol_5m": null,
        "volume_today": 1664901,
        "pct_gain": 14.81,
        "price": 4.73,
        "hod_price": 4.84,
        "pct_from_hod": -2.27,
        "at_hod": false,
        "near_hod": false,
        "is_active": true,
        "exclusion_reason": "NONE",
        "first_seen": "2025-12-30T23:24:18.719224+00:00",
        "last_evaluated": "2025-12-30T23:24:18.719224+00:00",
        "session_date": "2025-12-30",
        "has_valid_rel_vol": false,
        "has_valid_price": true
      },
      {
        "symbol": "WOK",
        "rank": 5,
        "dominance_score": 18.41,
        "gap_pct": 18.48,
        "rel_vol_daily": null,
        "rel_vol_5m": null,
        "volume_today": 993595,
        "pct_gain": 18.48,
        "price": 2.78,
        "hod_price": 3.3,
        "pct_from_hod": -15.76,
        "at_hod": false,
        "near_hod": false,
        "is_active": true,
        "exclusion_reason": "NONE",
        "first_seen": "2025-12-30T23:24:18.719224+00:00",
        "last_evaluated": "2025-12-30T23:24:18.719224+00:00",
        "session_date": "2025-12-30",
        "has_valid_rel_vol": false,
        "has_valid_price": true
      },
      {
        "symbol": "TTRX",
        "rank": 6,
        "dominance_score": 17.99,
        "gap_pct": 18.15,
        "rel_vol_daily": null,
        "rel_vol_5m": null,
        "volume_today": 109918,
        "pct_gain": 18.15,
        "price": 3.71,
        "hod_price": 3.93,
        "pct_from_hod": -5.6,
        "at_hod": false,
        "near_hod": false,
        "is_active": true,
        "exclusion_reason": "NONE",
        "first_seen": "2025-12-30T23:24:18.719224+00:00",
        "last_evaluated": "2025-12-30T23:24:18.719224+00:00",
        "session_date": "2025-12-30",
        "has_valid_rel_vol": false,
        "has_valid_price": true
      },
      {
        "symbol": "TROO",
        "rank": 7,
        "dominance_score": 17.75,
        "gap_pct": 17.96,
        "rel_vol_daily": null,
        "rel_vol_5m": null,
        "volume_today": 365515,
        "pct_gain": 17.96,
        "price": 2.89,
        "hod_price": 3.18,
        "pct_from_hod": -9.12,
        "at_hod": false,
        "near_hod": false,
        "is_active": true,
        "exclusion_reason": "NONE",
        "first_seen": "2025-12-30T23:24:18.719224+00:00",
        "last_evaluated": "2025-12-30T23:24:18.719224+00:00",
        "session_date": "2025-12-30",
        "has_valid_rel_vol": false,
        "has_valid_price": true
      },
      {
        "symbol": "SOPA",
        "rank": 8,
        "dominance_score": 16.18,
        "gap_pct": 16.72,
        "rel_vol_daily": null,
        "rel_vol_5m": null,
        "volume_today": 39270587,
        "pct_gain": 16.72,
        "price": 3.41,
        "hod_price": 3.8,
        "pct_from_hod": -10.26,
        "at_hod": false,
        "near_hod": false,
        "is_active": true,
        "exclusion_reason": "NONE",
        "first_seen": "2025-12-30T23:24:18.719224+00:00",
        "last_evaluated": "2025-12-30T23:24:18.719224+00:00",
        "session_date": "2025-12-30",
        "has_valid_rel_vol": false,
        "has_valid_price": true
      },
      {
        "symbol": "NOMA",
        "rank": 9,
        "dominance_score": 15.3,
        "gap_pct": 16.03,
        "rel_vol_daily": null,
        "rel_vol_5m": null,
        "volume_today": 243470,
        "pct_gain": 16.03,
        "price": 4.4,
        "hod_price": 5.31,
        "pct_from_hod": -17.14,
        "at_hod": false,
        "near_hod": false,
        "is_active": true,
        "exclusion_reason": "NONE",
        "first_seen": "2025-12-30T23:24:18.719224+00:00",
        "last_evaluated": "2025-12-30T23:24:18.719224+00:00",
        "session_date": "2025-12-30",
        "has_valid_rel_vol": false,
        "has_valid_price": true
      },
      {
        "symbol": "BNAI",
        "rank": 10,
        "dominance_score": 13.04,
        "gap_pct": 14.24,
        "rel_vol_daily": null,
        "rel_vol_5m": null,
        "volume_today": 5289675,
        "pct_gain": 14.24,
        "price": 2.14,
        "hod_price": 2.7299,
        "pct_from_hod": -21.61,
        "at_hod": false,
        "near_hod": false,
        "is_active": true,
        "exclusion_reason": "NONE",
        "first_seen": "2025-12-30T23:24:18.719224+00:00",
        "last_evaluated": "2025-12-30T23:24:18.719224+00:00",
        "session_date": "2025-12-30",
        "has_valid_rel_vol": false,
        "has_valid_price": true
      }
    ],
    "below_cutoff": [
      {
        "symbol": "NTRB",
        "rank": 11,
        "dominance_score": 12.28,
        "gap_pct": 13.64,
        "rel_vol_daily": null,
        "rel_vol_5m": null,
        "volume_today": 143456,
        "pct_gain": 13.64,
        "price": 4.81,
        "hod_price": 5.6595,
        "pct_from_hod": -15.01,
        "at_hod": false,
        "near_hod": false,
        "is_active": false,
        "exclusion_reason": "RANK_BELOW_CUTOFF",
        "first_seen": "2025-12-30T23:24:18.719224+00:00",
        "last_evaluated": "2025-12-30T23:24:18.719224+00:00",
        "session_date": "2025-12-30",
        "has_valid_rel_vol": false,
        "has_valid_price": true
      },
      {
        "symbol": "OPTX",
        "rank": 12,
        "dominance_score": 11.26,
        "gap_pct": 8.89,
        "rel_vol_daily": null,
        "rel_vol_5m": null,
        "volume_today": 947929,
        "pct_gain": 8.89,
        "price": 2.94,
        "hod_price": 3.09,
        "pct_from_hod": -4.85,
        "at_hod": false,
        "near_hod": false,
        "is_active": false,
        "exclusion_reason": "RANK_BELOW_CUTOFF",
        "first_seen": "2025-12-30T23:24:18.719224+00:00",
        "last_evaluated": "2025-12-30T23:24:18.719224+00:00",
        "session_date": "2025-12-30",
        "has_valid_rel_vol": false,
        "has_valid_price": true
      },
      {
        "symbol": "HIT",
        "rank": 13,
        "dominance_score": 10.74,
        "gap_pct": 12.43,
        "rel_vol_daily": null,
        "rel_vol_5m": null,
        "volume_today": 543119,
        "pct_gain": 12.43,
        "price": 1.62,
        "hod_price": 1.85,
        "pct_from_hod": -12.43,
        "at_hod": false,
        "near_hod": false,
        "is_active": false,
        "exclusion_reason": "RANK_BELOW_CUTOFF",
        "first_seen": "2025-12-30T23:24:18.719224+00:00",
        "last_evaluated": "2025-12-30T23:24:18.719224+00:00",
        "session_date": "2025-12-30",
        "has_valid_rel_vol": false,
        "has_valid_price": true
      },
      {
        "symbol": "BRAG",
        "rank": 14,
        "dominance_score": 8.83,
        "gap_pct": 3.02,
        "rel_vol_daily": null,
        "rel_vol_5m": null,
        "volume_today": 99091,
        "pct_gain": 3.02,
        "price": 2.05,
        "hod_price": 2.09,
        "pct_from_hod": -1.91,
        "at_hod": false,
        "near_hod": true,
        "is_active": false,
        "exclusion_reason": "RANK_BELOW_CUTOFF",
        "first_seen": "2025-12-30T23:24:18.719224+00:00",
        "last_evaluated": "2025-12-30T23:24:18.719224+00:00",
        "session_date": "2025-12-30",
        "has_valid_rel_vol": false,
        "has_valid_price": true
      },
      {
        "symbol": "DXST",
        "rank": 15,
        "dominance_score": 5.25,
        "gap_pct": 8.09,
        "rel_vol_daily": null,
        "rel_vol_5m": null,
        "volume_today": 2709629,
        "pct_gain": 8.09,
        "price": 1.25,
        "hod_price": 1.32,
        "pct_from_hod": -5.3,
        "at_hod": false,
        "near_hod": false,
        "is_active": false,
        "exclusion_reason": "RANK_BELOW_CUTOFF",
        "first_seen": "2025-12-30T23:24:18.719224+00:00",
        "last_evaluated": "2025-12-30T23:24:18.719224+00:00",
        "session_date": "2025-12-30",
        "has_valid_rel_vol": false,
        "has_valid_price": true
      },
      {
        "symbol": "ORBS",
        "rank": 16,
        "dominance_score": 5.02,
        "gap_pct": 7.91,
        "rel_vol_daily": null,
        "rel_vol_5m": null,
        "volume_today": 5336217,
        "pct_gain": 7.91,
        "price": 1.68,
        "hod_price": 1.93,
        "pct_from_hod": -12.95,
        "at_hod": false,
        "near_hod": false,
        "is_active": false,
        "exclusion_reason": "RANK_BELOW_CUTOFF",
        "first_seen": "2025-12-30T23:24:18.719224+00:00",
        "last_evaluated": "2025-12-30T23:24:18.719224+00:00",
        "session_date": "2025-12-30",
        "has_valid_rel_vol": false,
        "has_valid_price": true
      },
      {
        "symbol": "MMA",
        "rank": 17,
        "dominance_score": 4.2,
        "gap_pct": 7.26,
        "rel_vol_daily": null,
        "rel_vol_5m": null,
        "volume_today": 1182532,
        "pct_gain": 7.26,
        "price": 1.15,
        "hod_price": 1.42,
        "pct_from_hod": -19.01,
        "at_hod": false,
        "near_hod": false,
        "is_active": false,
        "exclusion_reason": "RANK_BELOW_CUTOFF",
        "first_seen": "2025-12-30T23:24:18.719224+00:00",
        "last_evaluated": "2025-12-30T23:24:18.719224+00:00",
        "session_date": "2025-12-30",
        "has_valid_rel_vol": false,
        "has_valid_price": true
      },
      {
        "symbol": "BBAI",
        "rank": 18,
        "dominance_score": 3.84,
        "gap_pct": 3.03,
        "rel_vol_daily": null,
        "rel_vol_5m": null,
        "volume_today": 42093556,
        "pct_gain": 3.03,
        "price": 5.4983,
        "hod_price": 5.7,
        "pct_from_hod": -3.54,
        "at_hod": false,
        "near_hod": false,
        "is_active": false,
        "exclusion_reason": "RANK_BELOW_CUTOFF",
        "first_seen": "2025-12-30T23:24:18.719224+00:00",
        "last_evaluated": "2025-12-30T23:24:18.719224+00:00",
        "session_date": "2025-12-30",
        "has_valid_rel_vol": false,
        "has_valid_price": true
      },
      {
        "symbol": "KULR",
        "rank": 19,
        "dominance_score": 3.22,
        "gap_pct": 2.54,
        "rel_vol_daily": null,
        "rel_vol_5m": null,
        "volume_today": 1609565,
        "pct_gain": 2.54,
        "price": 3.07,
        "hod_price": 3.17,
        "pct_from_hod": -3.15,
        "at_hod": false,
        "near_hod": false,
        "is_active": false,
        "exclusion_reason": "RANK_BELOW_CUTOFF",
        "first_seen": "2025-12-30T23:24:18.719224+00:00",
        "last_evaluated": "2025-12-30T23:24:18.719224+00:00",
        "session_date": "2025-12-30",
        "has_valid_rel_vol": false,
        "has_valid_price": true
      },
      {
        "symbol": "MSC",
        "rank": 20,
        "dominance_score": 3.08,
        "gap_pct": 6.38,
        "rel_vol_daily": null,
        "rel_vol_5m": null,
        "volume_today": 11561,
        "pct_gain": 6.38,
        "price": 3.67,
        "hod_price": 3.9,
        "pct_from_hod": -5.9,
        "at_hod": false,
        "near_hod": false,
        "is_active": false,
        "exclusion_reason": "RANK_BELOW_CUTOFF",
        "first_seen": "2025-12-30T23:24:18.719224+00:00",
        "last_evaluated": "2025-12-30T23:24:18.719224+00:00",
        "session_date": "2025-12-30",
        "has_valid_rel_vol": false,
        "has_valid_price": true
      }
    ],
    "excluded": [],
    "exclusion_summary": {},
    "ranking_proof": {
      "top_5": [
        {
          "rank": 1,
          "symbol": "FONR",
          "score": 39.3
        },
        {
          "rank": 2,
          "symbol": "ZBAI",
          "score": 32.91
        },
        {
          "rank": 3,
          "symbol": "ANL",
          "score": 21.04
        },
        {
          "rank": 4,
          "symbol": "NKLR",
          "score": 18.76
        },
        {
          "rank": 5,
          "symbol": "WOK",
          "score": 18.41
        }
      ],
      "recomputed_all": true,
      "force_fresh": true
    }
  },
  "watchlist_status": {
    "session_date": "2025-12-30",
    "cycle_count": 1,
    "last_recompute": "2025-12-30T23:24:18.719224+00:00",
    "active_count": 10,
    "total_candidates": 28,
    "archived_count": 0,
    "config": {
      "max_active_symbols": 10,
      "min_rel_vol_floor": 0.3,
      "min_price": 1.0,
      "max_price": 20.0,
      "min_gap_pct": 2.0,
      "enforce_session_boundary": true
    }
  },
  "timestamp": "2025-12-30T23:24:18.719224+00:00",
  "_meta": {
    "task_id": "DISCOVERY_GAPPERS",
    "status": "COMPLETED",
    "timestamp": "2025-12-30T17:24:18.719224",
    "duration_ms": 176395
  }
}