{
  "enabled": true,
  "paper_mode": true,
  "account_size": 1000.0,
  "risk_percent": 1.0,
  "use_risk_based_sizing": true,
  "max_position_size": 200.0,
  "max_shares": 500,
  "min_shares": 1,
  "min_spike_percent": 1.0,
  "min_volume_surge": 3.0,
  "max_spread_percent": 1.5,
  "min_price": 1.0,
  "max_price": 20.0,
  "profit_target_percent": 2.5,
  "stop_loss_percent": 1.5,
  "trailing_stop_percent": 1.0,
  "max_hold_seconds": 300,
  "reversal_candle_percent": 2.0,
  "macd_reversal_exit": true,
  "use_chronos_exit": false,
  "chronos_exit_min_hold": 30,
  "use_chronos_filter": false,
  "chronos_min_prob_up": 0.55,
  "use_order_flow_filter": false,
  "min_buy_pressure": 0.55,
  "use_regime_gating": true,
  "valid_regimes": [
    "TRENDING_UP",
    "RANGING",
    "VOLATILE",
    "TRENDING_DOWN"
  ],
  "use_signal_filter": false,
  "signal_min_confluence": 70.0,
  "signal_require_ema_bullish": false,
  "signal_require_macd_bullish": false,
  "signal_require_above_vwap": false,
  "use_scalp_fade_filter": false,
  "scalp_fade_threshold": 0.45,
  "scalp_continue_threshold": 0.55,
  "use_pullback_confirmation": false,
  "pullback_min_percent": 2.0,
  "pullback_max_percent": 10.0,
  "confirmation_break_percent": 0.5,
  "pullback_timeout_seconds": 120,
  "use_atr_stops": true,
  "atr_stop_multiplier": 1.5,
  "atr_target_multiplier": 2.0,
  "atr_trail_multiplier": 1.0,
  "failed_momentum_seconds": 60,
  "failed_momentum_threshold": 0.3,
  "use_velocity_filter": false,
  "min_entry_velocity": 0.1,
  "max_daily_loss": 200.0,
  "max_daily_trades": 1000,
  "cooldown_after_loss": 120,
  "blocked_hours": [
    11,
    12,
    13,
    14
  ],
  "blocked_time_start": 1100,
  "blocked_time_end": 1430,
  "volume_surge_max_hod_distance": 2.0,
  "use_warrior_filter": false,
  "warrior_min_grade": "C",
  "warrior_require_pattern": false,
  "warrior_require_tape_signal": false,
  "warrior_max_float": 20.0,
  "warrior_min_rvol": 2.0,
  "use_mtf_filter": false,
  "mtf_min_confidence": 60.0,
  "mtf_require_vwap_aligned": false,
  "mtf_require_macd_aligned": false,
  "use_vwap_filter": false,
  "vwap_max_extension_pct": 3.0,
  "use_vwap_trailing_stop": false,
  "vwap_stop_offset_pct": 0.3,
  "use_float_rotation_boost": true,
  "min_rotation_for_boost": 0.5,
  "require_low_float": false,
  "max_float_millions": 50.0,
  "use_exhaustion_exit": true,
  "exhaustion_exit_threshold": 70.0,
  "exhaustion_exit_on_divergence": true,
  "exhaustion_exit_on_red_candles": 5,
  "use_depth_analysis": false,
  "depth_require_bullish_imbalance": false,
  "depth_min_imbalance_ratio": 1.2,
  "depth_block_on_ask_wall": false,
  "use_gap_grader_filter": false,
  "gap_grader_min_grade": "C",
  "gap_grader_require_catalyst": false,
  "use_overnight_filter": false,
  "overnight_min_strength": "WEAK",
  "overnight_block_reversals": false,
  "use_low_float_analysis": false,
  "low_float_max_shares": 10.0,
  "low_float_min_volume_ratio": 5.0,
  "low_float_min_rotation": 50.0,
  "require_gating_approval": false,
  "allow_scout_trades": true,
  "scout_position_size_pct": 50,
  "scout_stop_loss_pct": 1.5,
  "scout_max_hold_seconds": 180,
  "use_state_machine": false,
  "state_machine_candidate_score": 30,
  "state_machine_igniting_score": 45,
  "state_machine_gated_score": 60,
  "use_extreme_mover_detection": true,
  "min_extreme_mover_percent": 15.0,
  "extreme_mover_min_volume": 300000,
  "auto_scan_enabled": true,
  "auto_scan_interval": 180,
  "auto_scan_add_to_watchlist": true,
  "auto_scan_max_symbols": 15,
  "auto_scan_types": [
    "momentum",
    "new_highs",
    "gainers"
  ],
  "use_probe_entries": true,
  "probe_size_multiplier": 0.3,
  "probe_stop_loss_percent": 1.5,
  "probe_min_micro_confidence": 0.5,
  "probe_max_per_symbol": 2,
  "probe_max_per_hour": 5,
  "probe_cooldown_minutes": 10,
  "watchlist": [
    "SPY",
    "QQQ",
    "AAPL",
    "TSLA",
    "NVDA"
  ],
  "blacklist": [
    "PAVS",
    "LHAI",
    "YCBD",
    "ADTX",
    "KLRS",
    "EUDA"
  ]
}